gitmess/__init__.py
gitmess/gitmess.py
gitmess-0.1.5.dist-info/LICENSE
gitmess-0.1.5.dist-info/METADATA
gitmess-0.1.5.dist-info/WHEEL
gitmess-0.1.5.dist-info/entry_points.txt
gitmess-0.1.5.dist-info/RECORD
