Metadata-Version: 2.1
Name: gitmess
Version: 0.1.5
Summary: 
Author: 0xjesus
Author-email: pdlgmcn@protonmail.com
Requires-Python: >=3.10,<4.0
Classifier: Programming Language :: Python :: 3
Classifier: Programming Language :: Python :: 3.10
Classifier: Programming Language :: Python :: 3.11
Requires-Dist: gitpython (>=3.1.37,<4.0.0)
Requires-Dist: langchain (>=0.0.300,<0.0.301)
Requires-Dist: openai (>=0.28.0,<0.29.0)
